{"id":1038086908,"shipment_date":"2022-02-18T09:55:36+01:00","date_time":"2022-02-18T09:55:36+01:00","pickup_point":false,"order_id":"1332178547","order_placed_date":"2022-02-16T10:55:21+01:00","shipment_details":{"salutation":"FEMALE","first_name":"R.","last_name":"Harder","address1":"House 22","address2":"Zichtweg","city":"NIEUW-VENNEP","country_code":"NL","zip":"2151WH","language":"nl"},"billing_details":{"salutation":"FEMALE","first_name":"R.","last_name":"Harder","address1":"House 22","address2":"Zichtweg","city":"NIEUW-VENNEP","country_code":"NL","zip":"2151WH"},"line_items":[{"id":"2855798427","offer":"9f87965b-ac66-441d-8c70-8b41d1762d8c","offer_reference":"5430002902036","product_title":"Moonbird adem- en slaapcoach Blue Green","product_ean":"5430002902036","quantity":1,"price":159,"unit_price":159,"commission":8.71,"fulfilment":{"method":"FBR","distribution_party":"RETAILER","latest_delivery_date":"2022-02-23"}}],"transport":{"transport_id":787890791,"transporter_code":"BPOST_BE","track_and_trace":"CD104453931BE"}}